normalize_pkgresources.py
normalize_pkgresources-0.1.dist-info/METADATA
normalize_pkgresources-0.1.dist-info/WHEEL
normalize_pkgresources-0.1.dist-info/top_level.txt
normalize_pkgresources-0.1.dist-info/RECORD
